kanimysql/__init__.py
kanimysql/core.py
kanimysql/cursor.py
kanimysql/func.py
kanimysql-0.0.4.dist-info/DESCRIPTION.rst
kanimysql-0.0.4.dist-info/METADATA
kanimysql-0.0.4.dist-info/RECORD
kanimysql-0.0.4.dist-info/WHEEL
kanimysql-0.0.4.dist-info/metadata.json
kanimysql-0.0.4.dist-info/top_level.txt
